ketamine/__init__.py
ketamine/cmyk.py
ketamine/colour.py
ketamine/hex.py
ketamine/hsl.py
ketamine/hsv.py
ketamine/lab.py
ketamine/rgb.py
ketamine/xyz.py
ketamine-1.0.1.dist-info/METADATA
ketamine-1.0.1.dist-info/WHEEL
ketamine-1.0.1.dist-info/licenses/LICENSE
ketamine-1.0.1.dist-info/RECORD
