Metadata-Version: 2.1
Name: ketamine
Version: 1.0.1
Summary: A robust python library for colour conversion between colour models.
Project-URL: Homepage, https://github.com/sertdfyguhi/ketamine
Project-URL: Bug Tracker, https://github.com/sertdfyguhi/ketamine/issues
Author: sertdfyguhi
License-File: LICENSE
Keywords: color,color conversion,colour,colour conversion,conversion,graphics,rgb
Classifier: Development Status :: 4 - Beta
Classifier: License :: OSI Approved :: GNU General Public License v2 (GPLv2)
Classifier: Operating System :: OS Independent
Classifier: Programming Language :: Python
Classifier: Programming Language :: Python :: 2.7
Classifier: Programming Language :: Python :: 3
Classifier: Programming Language :: Python :: 3.7
Classifier: Programming Language :: Python :: 3.8
Classifier: Programming Language :: Python :: 3.9
Classifier: Programming Language :: Python :: 3.10
Classifier: Programming Language :: Python :: 3.11
Classifier: Programming Language :: Python :: Implementation :: CPython
Classifier: Topic :: Multimedia :: Graphics
Classifier: Topic :: Multimedia :: Graphics :: Graphics Conversion
Classifier: Topic :: Scientific/Engineering :: Image Processing
Requires-Python: >=2.7
